{"last_refreshed": "2026-07-24 15:29:04 UTC", "reference_date": "2026-07-24", "city": {"id": 271, "name": "Prague", "country": "CZ"}, "phone_prefix": "420", "periods": [{"key": "prev_week", "label": "Previous week (Jul 6 - 12)", "short": "Previous week", "start": "2026-07-06", "end": "2026-07-12"}, {"key": "last_week", "label": "Last week (Jul 13 - 19)", "short": "Last week", "start": "2026-07-13", "end": "2026-07-19"}, {"key": "mtd", "label": "Month-to-Date (Jul 1 - 23)", "short": "MTD", "start": "2026-07-01", "end": "2026-07-23"}], "di_breakdown": {"prev_week": {"label": "Previous week (Jul 6 - 12)", "short": "Previous week", "start": "2026-07-06", "end": "2026-07-12", "rows": [{"segment": "TOTAL_PRAGUE", "orders": 62157, "active_users": 38864, "gmv_eur": 1380563.0, "bolt_spend_eur": 151924.0, "aov_eur": 22.22, "di_pct": 11.0, "pct_of_bolt_spend": 100.0, "pct_of_gmv": 100.0}, {"segment": "expat", "orders": 5174, "active_users": 3077, "gmv_eur": 125829.0, "bolt_spend_eur": 11211.0, "aov_eur": 24.35, "di_pct": 8.91, "pct_of_bolt_spend": 7.38, "pct_of_gmv": 9.11}, {"segment": "local", "orders": 55268, "active_users": 34617, "gmv_eur": 1208610.0, "bolt_spend_eur": 137880.0, "aov_eur": 21.88, "di_pct": 11.41, "pct_of_bolt_spend": 90.76, "pct_of_gmv": 87.54}, {"segment": "tourist", "orders": 1713, "active_users": 1168, "gmv_eur": 46098.0, "bolt_spend_eur": 2833.0, "aov_eur": 26.91, "di_pct": 6.15, "pct_of_bolt_spend": 1.86, "pct_of_gmv": 3.34}, {"segment": "unknown", "orders": 2, "active_users": 2, "gmv_eur": 27.0, "bolt_spend_eur": 0.0, "aov_eur": 13.45, "di_pct": 0.0, "pct_of_bolt_spend": 0.0, "pct_of_gmv": 0.0}]}, "last_week": {"label": "Last week (Jul 13 - 19)", "short": "Last week", "start": "2026-07-13", "end": "2026-07-19", "rows": [{"segment": "TOTAL_PRAGUE", "orders": 64871, "active_users": 40078, "gmv_eur": 1450839.0, "bolt_spend_eur": 156263.0, "aov_eur": 22.37, "di_pct": 10.77, "pct_of_bolt_spend": 100.0, "pct_of_gmv": 100.0}, {"segment": "expat", "orders": 5561, "active_users": 3389, "gmv_eur": 133797.0, "bolt_spend_eur": 11711.0, "aov_eur": 24.07, "di_pct": 8.75, "pct_of_bolt_spend": 7.49, "pct_of_gmv": 9.22}, {"segment": "local", "orders": 57667, "active_users": 35591, "gmv_eur": 1273280.0, "bolt_spend_eur": 141834.0, "aov_eur": 22.08, "di_pct": 11.14, "pct_of_bolt_spend": 90.77, "pct_of_gmv": 87.76}, {"segment": "tourist", "orders": 1643, "active_users": 1098, "gmv_eur": 43761.0, "bolt_spend_eur": 2718.0, "aov_eur": 26.63, "di_pct": 6.21, "pct_of_bolt_spend": 1.74, "pct_of_gmv": 3.02}]}, "mtd": {"label": "Month-to-Date (Jul 1 - 23)", "short": "MTD", "start": "2026-07-01", "end": "2026-07-23", "rows": [{"segment": "TOTAL_PRAGUE", "orders": 206041, "active_users": 82421, "gmv_eur": 4558943.0, "bolt_spend_eur": 495633.0, "aov_eur": 22.13, "di_pct": 10.87, "pct_of_bolt_spend": 100.0, "pct_of_gmv": 100.0}, {"segment": "expat", "orders": 17442, "active_users": 7240, "gmv_eur": 415117.0, "bolt_spend_eur": 36661.0, "aov_eur": 23.81, "di_pct": 8.83, "pct_of_bolt_spend": 7.4, "pct_of_gmv": 9.11}, {"segment": "local", "orders": 182927, "active_users": 71762, "gmv_eur": 3993526.0, "bolt_spend_eur": 449776.0, "aov_eur": 21.84, "di_pct": 11.26, "pct_of_bolt_spend": 90.75, "pct_of_gmv": 87.6}, {"segment": "tourist", "orders": 5663, "active_users": 3414, "gmv_eur": 150150.0, "bolt_spend_eur": 9183.0, "aov_eur": 26.52, "di_pct": 6.12, "pct_of_bolt_spend": 1.85, "pct_of_gmv": 3.29}, {"segment": "unknown", "orders": 9, "active_users": 5, "gmv_eur": 150.0, "bolt_spend_eur": 12.0, "aov_eur": 16.64, "di_pct": 8.21, "pct_of_bolt_spend": 0.0, "pct_of_gmv": 0.0}]}}}