{"last_refreshed": "2026-05-26 07:46:50 UTC", "reference_date": "2026-05-26", "city": {"id": 271, "name": "Prague", "country": "CZ"}, "phone_prefix": "420", "periods": [{"key": "prev_week", "label": "Previous week (May 11 - 17)", "short": "Previous week", "start": "2026-05-11", "end": "2026-05-17"}, {"key": "last_week", "label": "Last week (May 18 - 24)", "short": "Last week", "start": "2026-05-18", "end": "2026-05-24"}, {"key": "mtd", "label": "Month-to-Date (May 1 - 25)", "short": "MTD", "start": "2026-05-01", "end": "2026-05-25"}], "di_breakdown": {"prev_week": {"label": "Previous week (May 11 - 17)", "short": "Previous week", "start": "2026-05-11", "end": "2026-05-17", "rows": [{"segment": "TOTAL_PRAGUE", "orders": 75600, "active_users": 46427, "gmv_eur": 1678368.0, "bolt_spend_eur": 209991.0, "aov_eur": 22.21, "di_pct": 12.51, "pct_of_bolt_spend": 100.0, "pct_of_gmv": 100.0}, {"segment": "expat", "orders": 6327, "active_users": 3765, "gmv_eur": 147151.0, "bolt_spend_eur": 13792.0, "aov_eur": 23.27, "di_pct": 9.37, "pct_of_bolt_spend": 6.57, "pct_of_gmv": 8.77}, {"segment": "local", "orders": 68147, "active_users": 41892, "gmv_eur": 1499816.0, "bolt_spend_eur": 194457.0, "aov_eur": 22.01, "di_pct": 12.97, "pct_of_bolt_spend": 92.6, "pct_of_gmv": 89.36}, {"segment": "tourist", "orders": 1123, "active_users": 768, "gmv_eur": 31314.0, "bolt_spend_eur": 1742.0, "aov_eur": 27.93, "di_pct": 5.56, "pct_of_bolt_spend": 0.83, "pct_of_gmv": 1.87}, {"segment": "unknown", "orders": 3, "active_users": 2, "gmv_eur": 88.0, "bolt_spend_eur": 1.0, "aov_eur": 29.18, "di_pct": 1.38, "pct_of_bolt_spend": 0.0, "pct_of_gmv": 0.01}]}, "last_week": {"label": "Last week (May 18 - 24)", "short": "Last week", "start": "2026-05-18", "end": "2026-05-24", "rows": [{"segment": "TOTAL_PRAGUE", "orders": 70293, "active_users": 43718, "gmv_eur": 1533497.0, "bolt_spend_eur": 155683.0, "aov_eur": 21.82, "di_pct": 10.15, "pct_of_bolt_spend": 100.0, "pct_of_gmv": 100.0}, {"segment": "expat", "orders": 5987, "active_users": 3558, "gmv_eur": 137935.0, "bolt_spend_eur": 10490.0, "aov_eur": 23.04, "di_pct": 7.6, "pct_of_bolt_spend": 6.74, "pct_of_gmv": 8.99}, {"segment": "local", "orders": 63070, "active_users": 39311, "gmv_eur": 1361897.0, "bolt_spend_eur": 143473.0, "aov_eur": 21.6, "di_pct": 10.53, "pct_of_bolt_spend": 92.16, "pct_of_gmv": 88.81}, {"segment": "tourist", "orders": 1236, "active_users": 849, "gmv_eur": 33664.0, "bolt_spend_eur": 1720.0, "aov_eur": 27.3, "di_pct": 5.11, "pct_of_bolt_spend": 1.1, "pct_of_gmv": 2.2}]}, "mtd": {"label": "Month-to-Date (May 1 - 25)", "short": "MTD", "start": "2026-05-01", "end": "2026-05-25", "rows": [{"segment": "TOTAL_PRAGUE", "orders": 252690, "active_users": 92630, "gmv_eur": 5551481.0, "bolt_spend_eur": 639584.0, "aov_eur": 21.97, "di_pct": 11.52, "pct_of_bolt_spend": 100.0, "pct_of_gmv": 100.0}, {"segment": "expat", "orders": 21690, "active_users": 8099, "gmv_eur": 501238.0, "bolt_spend_eur": 43681.0, "aov_eur": 23.12, "di_pct": 8.71, "pct_of_bolt_spend": 6.83, "pct_of_gmv": 9.03}, {"segment": "local", "orders": 226672, "active_users": 81842, "gmv_eur": 4933463.0, "bolt_spend_eur": 589937.0, "aov_eur": 21.77, "di_pct": 11.96, "pct_of_bolt_spend": 92.24, "pct_of_gmv": 88.87}, {"segment": "tourist", "orders": 4318, "active_users": 2684, "gmv_eur": 116491.0, "bolt_spend_eur": 5956.0, "aov_eur": 27.01, "di_pct": 5.11, "pct_of_bolt_spend": 0.93, "pct_of_gmv": 2.1}, {"segment": "unknown", "orders": 10, "active_users": 5, "gmv_eur": 289.0, "bolt_spend_eur": 9.0, "aov_eur": 28.86, "di_pct": 3.17, "pct_of_bolt_spend": 0.0, "pct_of_gmv": 0.01}]}}}